klvdata/__init__.py
klvdata/common.py
klvdata/element.py
klvdata/elementparser.py
klvdata/klvparser.py
klvdata/misb0102.py
klvdata/misb0601.py
klvdata/setparser.py
klvdata/streamparser.py
klvdata-0.0.3.dist-info/METADATA
klvdata-0.0.3.dist-info/RECORD
klvdata-0.0.3.dist-info/WHEEL
klvdata-0.0.3.dist-info/top_level.txt
