Metadata-Version: 2.1
Name: klvdata
Version: 0.0.3
Summary: A Python library for parsing MISB/STANAG 4609 Key Length Value (KLV) metadata.
Home-page: https://github.com/paretech/klvdata/
Author: paretech
Author-email: paretech@gmail.com
License: MIT
Keywords: STANAG 4609,MISB,KLV,Metadata,Video
Platform: UNKNOWN
Classifier: Development Status :: 3 - Alpha
Classifier: Intended Audience :: Developers
Classifier: Topic :: Multimedia :: Video :: Conversion
Classifier: Topic :: Scientific/Engineering :: GIS
Classifier: Topic :: Scientific/Engineering :: Information Analysis
Classifier: Topic :: Software Development :: Libraries
Classifier: License :: OSI Approved :: MIT License
Classifier: Programming Language :: Python :: 3.5
Classifier: Programming Language :: Python :: 3.6
Classifier: Programming Language :: Python :: 3.7
Classifier: Programming Language :: Python :: 3 :: Only
Requires-Python: >=3.5
